{
	"format_version": "1.10.0",
	"minecraft:attachable": {
		"description": {
			"identifier": "lc:scpdy_knife",
			"materials": {
				"default": "entity_alphatest"
			},
			"textures": {
				"default": "textures/scpdy/knife"
			},
			"geometry": {
				"default": "geometry.scpdy_knife"
			},
			"animations": {
				"anim.fp_general": "animation.scpdy_knife.fp_general"
			},
			"scripts": {
				"animate": [
					{
						"anim.fp_general": "c.is_first_person"
					}
				]
			},
			"render_controllers": ["controller.render.scpdy.standard"]
		}
	}
}
