{
	"format_version": "1.21.10",
	"minecraft:item": {
		"description": {
			"identifier": "lc:scpdy_gun_glock17_mag",
			"menu_category": {
				"category": "none",
				"group": "itemGroup.name.items",
				"is_hidden_in_commands": true
			}
		},
		"components": {
			"minecraft:custom_components": ["scpdy:mag", "scpdy:dont_get_durability_damage_on_hit"],
			"minecraft:max_stack_size": 1,
			"minecraft:icon": {
				"textures": {
					"default": "scpdy_gun_glock17_mag_icon"
				}
			},
			"minecraft:hand_equipped": true,
			"minecraft:allow_off_hand": true,
			"minecraft:durability": {
				"damage_chance": {
					"min": 0,
					"max": 0
				},
				"max_durability": 17
			},
			"minecraft:display_name": {
				"value": "item.lc:scpdy_gun_glock17_mag.name"
			},
			"minecraft:glint": false,
			"minecraft:tags": {
				"tags": ["mag", "scpdy:mag", "scpdy:ammo_loadable", "ammo_type:9mm"]
			}
		}
	}
}
