{
	"format_version": "1.10.0",
	"minecraft:client_entity": {
		"description": {
			"identifier": "lc:scpdy_pwr_node",
			"materials": {
				"default": "entity_emissive_alpha_one_sided"
			},
			"textures": {
				"default": "textures/scpdy/pwrgrid/pwr_node"
			},
			"geometry": {
				"default": "geometry.scpdy_pwr_node"
			},
			"animations": {
				"anim.general": "animation.scpdy_pwr_node.general"
			},
			"scripts": {
				"animate": ["anim.general"],
				"initialize": [
					"v.is_powered = false;",
					"v.rot_x = 0.0;",
					"v.rot_y = 0.0;"
				],
				"pre_animation": [
					"v.is_powered = q.property('lc:is_powered');",
					"v.rot_x = q.property('lc:rot_x');",
					"v.rot_y = q.property('lc:rot_y');"
				]
			},
			"render_controllers": ["controller.render.scpdy.pwrgrid.pwr_node"]
		}
	}
}
