{
	"format_version": "1.21.80",
	"minecraft:block": {
		"description": {
			"identifier": "lc:scpdy_kr_1",
			"menu_category": {
				"category": "construction"
			},
			"states": {
				"lc:is_on": [false, true],
				"lc:clearance_level": [0, 1, 2, 3, 4, 5, 6],
				"lc:mode": ["powerActivators", "ctrlBlastDoor", "placeRbBelow", "placeRbBehind"]
			},
			"traits": {
				"minecraft:placement_direction": {
					"enabled_states": ["minecraft:cardinal_direction"],
					"y_rotation_offset": 180
				}
			}
		},
		"components": {
			"scpdy:kr": {},
			"minecraft:geometry": {
				"identifier": "geometry.scpdy_kr_1",
				"bone_visibility": {
					"lamp_off": "!q.block_state('lc:is_on')",
					"lamp_on": "q.block_state('lc:is_on')",
					"color_lvl_0": "q.block_state('lc:clearance_level') == 0",
					"color_lvl_1": "q.block_state('lc:clearance_level') == 1",
					"color_lvl_2": "q.block_state('lc:clearance_level') == 2",
					"color_lvl_3": "q.block_state('lc:clearance_level') == 3",
					"color_lvl_4": "q.block_state('lc:clearance_level') == 4",
					"color_lvl_5": "q.block_state('lc:clearance_level') == 5",
					"color_o5": "q.block_state('lc:clearance_level') == 6"
				}
			},
			"minecraft:item_visual": {
				"geometry": {
					"identifier": "geometry.scpdy_kr_1",
					"bone_visibility": {
						"lamp_off": true,
						"lamp_on": false,
						"color_lvl_0": false,
						"color_lvl_1": false,
						"color_lvl_2": true,
						"color_lvl_3": false,
						"color_lvl_4": false,
						"color_lvl_5": false,
						"color_o5": false
					}
				},
				"material_instances": {
					"*": {
						"texture": "scpdy_kr_1",
						"render_method": "opaque"
					}
				}
			},
			"minecraft:material_instances": {
				"*": {
					"texture": "scpdy_kr_1",
					"render_method": "opaque"
				}
			},
			"minecraft:destruction_particles": {
				"texture": "scpdy_cst_reinforced_panel_3"
			},
			"minecraft:destructible_by_explosion": {
				"explosion_resistance": 2.5
			},
			"minecraft:destructible_by_mining": {
				"seconds_to_destroy": 0.2
			},
			"minecraft:tick": {
				"interval_range": [2000, 3000],
				"looping": true
			},
			"minecraft:collision_box": false,
			"minecraft:selection_box": {
				"origin": [-2, 5, 7],
				"size": [4, 6, 1]
			},
			"tag:lc:machinery": {},
			"tag:lc:machinery_input": {},
			"tag:lc:keycard_reader": {},
			"tag:lc:kr": {}
		},
		"permutations": [
			{
				"condition": "q.block_state('lc:is_on')",
				"components": {
					"minecraft:tick": {
						"interval_range": [8, 8],
						"looping": true
					}
				}
			},
			{
				"condition": "q.block_state('minecraft:cardinal_direction') == 'north'",
				"components": {
					"minecraft:transformation": { "rotation": [0, 0, 0] }
				}
			},
			{
				"condition": "q.block_state('minecraft:cardinal_direction') == 'south'",
				"components": {
					"minecraft:transformation": { "rotation": [0, 180, 0] }
				}
			},
			{
				"condition": "q.block_state('minecraft:cardinal_direction') == 'west'",
				"components": {
					"minecraft:transformation": { "rotation": [0, 90, 0] }
				}
			},
			{
				"condition": "q.block_state('minecraft:cardinal_direction') == 'east'",
				"components": {
					"minecraft:transformation": { "rotation": [0, 270, 0] }
				}
			}
		]
	}
}
